nsd_mcp_sqlite_server/__init__.py
nsd_mcp_sqlite_server/__main__.py
nsd_mcp_sqlite_server/nsd_mcp_sqlite_server.py
nsd_mcp_sqlite_server-0.1.0.dist-info/METADATA
nsd_mcp_sqlite_server-0.1.0.dist-info/WHEEL
nsd_mcp_sqlite_server-0.1.0.dist-info/entry_points.txt
nsd_mcp_sqlite_server-0.1.0.dist-info/RECORD
