Metadata-Version: 2.4
Name: nsd-mcp-sqlite-server
Version: 0.1.0
Summary: SQLite test server
Requires-Python: >=3.11
Requires-Dist: build>=1.3.0
Requires-Dist: mcp[cli]>=1.21.0
Requires-Dist: twine>=6.2.0
